file_ops_agent/__init__.py
file_ops_agent/cli.py
file_ops_agent-0.1.1.dist-info/LICENSE
file_ops_agent-0.1.1.dist-info/METADATA
file_ops_agent-0.1.1.dist-info/WHEEL
file_ops_agent-0.1.1.dist-info/entry_points.txt
file_ops_agent-0.1.1.dist-info/top_level.txt
file_ops_agent-0.1.1.dist-info/RECORD
