Metadata-Version: 2.1
Name: file_ops_agent
Version: 0.1.1
Summary: Command-line file operations agent
Home-page: https://github.com/yourusername/file_ops_agent
Author: Your Name
Author-email: your.email@example.com
License: MIT
Classifier: Programming Language :: Python :: 3
Classifier: License :: OSI Approved :: MIT License
Classifier: Operating System :: OS Independent
Requires-Python: >=3.6
License-File: LICENSE
